loggraph/__init__.py
loggraph/accumulator.py
loggraph/loggen.py
loggraph/loggraph.py
loggraph/main.py
loggraph/parser.py
loggraph-0.0.2.dist-info/DESCRIPTION.rst
loggraph-0.0.2.dist-info/METADATA
loggraph-0.0.2.dist-info/RECORD
loggraph-0.0.2.dist-info/WHEEL
loggraph-0.0.2.dist-info/entry_points.txt
loggraph-0.0.2.dist-info/metadata.json
loggraph-0.0.2.dist-info/top_level.txt
