Metadata-Version: 2.0
Name: loggraph
Version: 0.0.2
Summary: UNKNOWN
Home-page: https://github.com/bpicolo/loggraph
Author: Ben Picolo
Author-email: be.picolo@gmail.com
License: UNKNOWN
Platform: UNKNOWN
Requires-Dist: bokeh
Requires-Dist: ciso8601
Requires-Dist: pandas
Requires-Dist: python-dateutil
Requires-Dist: ujson
